toolbox/__init__.py
toolbox/utility.py
toolbox/container/__init__.py
toolbox/container/bound_func_as_cls_method.py
toolbox/container/namedtuple_from_dict.py
toolbox/dao/__init__.py
toolbox/dao/data_migrator.py
toolbox/dao/dtype_mapping.py
toolbox/dao/dtypes.py
toolbox/dao/feed.py
toolbox/dao/connector/__init__.py
toolbox/dao/connector/blob_connector.py
toolbox/dao/connector/db_connector.py
toolbox/dao/connector/excel_connector.py
toolbox/dao/connector/no_sql_db_connector.py
toolbox/dao/connector/sqlite_connector.py
toolbox/dao/convertor/__init__.py
toolbox/dao/convertor/convertor.py
toolbox/dao/convertor/convertor_methods_mapper.py
toolbox/dao/convertor/from_file_loader.py
toolbox/dao/convertor/utility.py
toolbox/dao/data_spec/__init__.py
toolbox/dao/data_spec/data_specification.py
toolbox/dao/files/__init__.py
toolbox/dao/files/dtype_detect.py
toolbox/dao/files/ftype_detect.py
toolbox/dao/files/loader.py
toolbox/dao/files/utility.py
toolbox/metaheuristic/__init__.py
toolbox/optimization/__init__.py
toolbox/optimization/docplex/__init__.py
toolbox/optimization/docplex/model.py
toolbox/optimization/docplex/model_feed.py
toolbox/optimization/docplex/procedure.py
toolbox/stats/__init__.py
toolbox/streamlit/__init__.py
toolbox/streamlit/component/__init__.py
toolbox/streamlit/component/blob_container_explorer.py
toolbox/streamlit/component/supplement.py
toolbox/streamlit/component/whiteboard.py
toolbox/streamlit/toybox/__init__.py
toolbox/streamlit/toybox/toybox.py
toolbox/streamlit/toybox/toybox_functions.py
toolbox/string/__init__.py
toolbox/string/convert_functions.py
toolbox/string/sql.py
toolbox/watcher/__init__.py
toolbox/watcher/get_obj_size.py
toolbox/watcher/timeit.py
liamhsieh_toolbox-0.3.6.12.dist-info/LICENSE
liamhsieh_toolbox-0.3.6.12.dist-info/METADATA
liamhsieh_toolbox-0.3.6.12.dist-info/WHEEL
liamhsieh_toolbox-0.3.6.12.dist-info/top_level.txt
liamhsieh_toolbox-0.3.6.12.dist-info/RECORD
